offline_docs/__init__.py
offline_docs/cli.py
offline_docs/dependencies.py
offline_docs/download.py
offline_docs/paths.py
offline_docs-0.3.3.dist-info/entry_points.txt
offline_docs-0.3.3.dist-info/LICENSE
offline_docs-0.3.3.dist-info/WHEEL
offline_docs-0.3.3.dist-info/METADATA
offline_docs-0.3.3.dist-info/RECORD
