Metadata-Version: 2.1
Name: offline-docs
Version: 0.3.3
Summary: CLI to quickly access docs of Python libraries, supporing offline usage.
Author: top-on
Author-email: top-on@posteo.de
Requires-Python: >=3.8,<4.0
Classifier: Programming Language :: Python :: 3
Classifier: Programming Language :: Python :: 3.10
Classifier: Programming Language :: Python :: 3.8
Classifier: Programming Language :: Python :: 3.9
Requires-Dist: typer (>=0.4.0,<0.5.0)
Requires-Dist: urlpath (>=1.2.0,<2.0.0)
Requires-Dist: wget (>=3.2,<4.0)
Project-URL: repository, https://github.com/top-on/offline-docs
